as/ok.py
donghun-0.0.1.dist-info/METADATA
donghun-0.0.1.dist-info/WHEEL
donghun-0.0.1.dist-info/top_level.txt
donghun-0.0.1.dist-info/RECORD
