Metadata-Version: 2.1
Name: donghun
Version: 0.0.1
Summary: oss-dev my calculator 0001
Download-URL: https://github.com/Rriw/my-oss/archive/refs/tags/v0.0.9.zip
Author: Rriw
Author-email: alex04220126@gmail.com
Classifier: Programming Language :: Python :: 3.7
